clwe/__init__.py
clwe/cli.py
clwe/core/__init__.py
clwe/core/batch_operations.py
clwe/core/chromacrypt_kem.py
clwe/core/chromacrypt_sign.py
clwe/core/chromacrypt_sign_optimized.py
clwe/core/color_cipher.py
clwe/core/color_hash.py
clwe/core/document_signer.py
clwe/core/hardware_acceleration.py
clwe/core/ntt_engine.py
clwe/core/parameters.py
clwe/core/production_optimizations.py
clwe/core/side_channel_protection.py
clwe/core/transforms.py
clwe/examples/__init__.py
clwe/examples/advanced_usage.py
clwe/examples/basic_usage.py
clwe/examples/colorhash_image_demo.py
clwe/examples/document_signing_demo.py
clwe/examples/enhanced_colorhash_demo.py
clwe/utils/__init__.py
clwe/utils/performance.py
clwe/utils/serialization.py
clwe/utils/validation.py
cryptopix_clwe-1.0.0.dist-info/licenses/LICENSE
cryptopix_clwe-1.0.0.dist-info/METADATA
cryptopix_clwe-1.0.0.dist-info/WHEEL
cryptopix_clwe-1.0.0.dist-info/entry_points.txt
cryptopix_clwe-1.0.0.dist-info/top_level.txt
cryptopix_clwe-1.0.0.dist-info/RECORD
