Metadata-Version: 2.4
Name: cryptopix-clwe
Version: 1.0.0
Summary: CLWE - Revolutionary Post-Quantum Cryptography with Color Transformations
Home-page: https://github.com/cryptopix-dev/cryptopix-clwe
Author: Cryptopix Development Team
Author-email: Cryptopix Development Team <support@cryptopix.in>
Maintainer-email: Cryptopix Development Team <support@cryptopix.in>
License: MIT
Project-URL: Homepage, https://www.cryptopix.in
Project-URL: Documentation, https://github.com/cryptopix-dev/cryptopix-clwe
Project-URL: Repository, https://github.com/cryptopix-dev/cryptopix-clwe
Project-URL: Issues, https://github.com/cryptopix-dev/cryptopix-clwe/issues
Project-URL: Changelog, https://github.com/cryptopix-dev/cryptopix-clwe/blob/main/CHANGELOG.md
Keywords: cryptography,post-quantum,lattice-based,color-transformation,security,encryption,quantum-resistant
Classifier: Development Status :: 5 - Production/Stable
Classifier: Intended Audience :: Developers
Classifier: Intended Audience :: Information Technology
Classifier: Intended Audience :: Science/Research
Classifier: License :: OSI Approved :: MIT License
Classifier: Operating System :: OS Independent
Classifier: Programming Language :: Python :: 3
Classifier: Programming Language :: Python :: 3.8
Classifier: Programming Language :: Python :: 3.9
Classifier: Programming Language :: Python :: 3.10
Classifier: Programming Language :: Python :: 3.11
Classifier: Programming Language :: Python :: 3.12
Classifier: Topic :: Security :: Cryptography
Classifier: Topic :: Software Development :: Libraries :: Python Modules
Requires-Python: >=3.8
License-File: LICENSE
Requires-Dist: numpy>=1.21.0
Requires-Dist: cryptography>=3.4.0
Requires-Dist: Pillow>=8.0.0
Provides-Extra: dev
Requires-Dist: pytest>=6.0.0; extra == "dev"
Requires-Dist: pytest-cov>=2.0.0; extra == "dev"
Requires-Dist: black>=21.0.0; extra == "dev"
Requires-Dist: flake8>=3.9.0; extra == "dev"
Requires-Dist: mypy>=0.800; extra == "dev"
Requires-Dist: sphinx>=4.0.0; extra == "dev"
Requires-Dist: sphinx-rtd-theme>=0.5.0; extra == "dev"
Provides-Extra: gpu
Requires-Dist: cupy>=9.0.0; extra == "gpu"
Provides-Extra: full
Requires-Dist: numpy>=1.21.0; extra == "full"
Requires-Dist: cryptography>=3.4.0; extra == "full"
Requires-Dist: Pillow>=8.0.0; extra == "full"
Requires-Dist: cupy>=9.0.0; extra == "full"
Requires-Dist: scipy>=1.7.0; extra == "full"
Dynamic: author
Dynamic: home-page
Dynamic: license-file
Dynamic: requires-python
